<?xml version="1.0" encoding="utf-8"?>

<LanguageData>

  <AWL_PenetratingPowerLabel>Penetration Power</AWL_PenetratingPowerLabel>
  <AWL_PenetratingPowerText>The bullets of this weapon possess penetration capability. They can cause damage to a number of units equivalent to the penetration power value at most.</AWL_PenetratingPowerText>

  <AWL_ShieldPenetrationLabel>Shield Penetration Ability</AWL_ShieldPenetrationLabel>
  <AWL_ShieldPenetrationText>Whether the bullets of this weapon can penetrate shields.</AWL_ShieldPenetrationText>
  <AWL_PenetratingPowerCostByShield>Penetration power consumption for shield penetration</AWL_PenetratingPowerCostByShield>
</LanguageData>